__init__.py
conftest.py
example.cgi
nanosax.py
setup.py
templess.py
version.txt
./__init__.py
./conftest.py
./nanosax.py
./templess.py
apigen/apigen.py
apigen/layout.py
apigen/project.py
apigen/style.css
doc/CHERRYPY.txt
doc/INSTALL.txt
doc/LICENSE.txt
doc/README.txt
doc/conftest.py
templates/cgierror.html
templates/cgitest.html
templess.egg-info/PKG-INFO
templess.egg-info/SOURCES.txt
templess.egg-info/dependency_links.txt
templess.egg-info/entry_points.txt
templess.egg-info/not-zip-safe
templess.egg-info/requires.txt
templess.egg-info/top_level.txt
test/__init__.py
test/oneshot.py
test/speedtest.py
test/templess.rng
test/test_nanosax.py
test/test_templess.py
test/test_templess_functional.py
test/xhtml.rng
test/data/test1.xml
test/data/nsxml/failing_note.xml
test/data/nsxml/working_10orMoreProductAandProductB.xml
test/data/nsxml/working_10orMoreProductAandProductB.xsl.xml
test/data/nsxml/working_Cheapest10Products.xml
test/data/nsxml/working_Cheapest10Products.xsl.xml
test/data/nsxml/working_EmployeesCompanyAndLanguage.xml
test/data/nsxml/working_EmployeesCompanyAndLanguage.xsl.xml
test/data/nsxml/working_EmployeesInternetNonXML.xml
test/data/nsxml/working_EmployeesInternetNonXML.xsl.xml
test/data/nsxml/working_HighestPaidEmployees.xml
test/data/nsxml/working_HighestPaidEmployees.xsl.xml
test/data/nsxml/working_HighestWidgetSales.xml
test/data/nsxml/working_HighestWidgetSales.xsl.xml
test/data/nsxml/working_TopNProductsPerSeason.xsl.xml
test/data/nsxml/working_cd_catalog.xml
test/data/nsxml/working_cmc.xml
test/data/nsxml/working_kupubook.xml
test/data/nsxml/working_node_ex_dtd.xml
test/data/nsxml/working_node_in_dtd.xml
test/data/nsxml/working_note.xml
test/data/nsxml/working_plant_catalog.xml
test/data/nsxml/working_simple.xml
test/data/nsxml/working_xml_note.xml
test/modules/applet.rng
test/modules/attribs.rng
test/modules/base.rng
test/modules/basic-form.rng
test/modules/basic-table.rng
test/modules/bdo.rng
test/modules/csismap.rng
test/modules/datatypes.rng
test/modules/edit.rng
test/modules/events.rng
test/modules/form.rng
test/modules/frames.rng
test/modules/hypertext.rng
test/modules/iframe.rng
test/modules/image.rng
test/modules/inlstyle.rng
test/modules/legacy.rng
