Metadata-Version: 1.0
Name: templess
Version: 0.3
Summary: Templess templating system
Home-page: http://templess.johnnydebris.net/
Author: Guido Wesdorp
Author-email: johnny@johnnydebris.net
License: UNKNOWN
Keywords: templess
Platform: UNKNOWN
Classifier: Development Status :: 3 - Alpha
Classifier: Environment :: Web Environment
Classifier: Intended Audience :: Developers
Classifier: License :: OSI Approved :: Zope Public License
Classifier: Programming Language :: Python
Classifier: Operating System :: OS Independent
Classifier: Topic :: Internet :: WWW/HTTP
